README.rst
setup.py
validation-files.yaml
validation-options.yaml
listlessview/__init__.py
listlessview/configure.zcml
listlessview/interfaces.py
listlessview/views.py
listlessview.egg-info/PKG-INFO
listlessview.egg-info/SOURCES.txt
listlessview.egg-info/dependency_links.txt
listlessview.egg-info/entry_points.txt
listlessview.egg-info/requires.txt
listlessview.egg-info/top_level.txt
listlessview/locales/README.txt
listlessview/profiles/default/browserlayer.xml
listlessview/profiles/default/types/Folder.xml
listlessview/templates/README.txt
listlessview/templates/listless.pt