Metadata-Version: 1.0
Name: listlessview
Version: 0.1.3
Summary: Provide empty folder listing view for Plone folders
Home-page: https://github.com/miohtama/listlessview
Author: Mikko Ohtamaa
Author-email: mikko@opensourcehacker.com
License: GPL2
Platform: UNKNOWN
Classifier: Framework :: Plone
Classifier: Programming Language :: Python
